direqt/__init__.py
direqt/direqt.py
direqt/rbm.py
direqt/util.py
direqt-1.0.0.dist-info/LICENSE
direqt-1.0.0.dist-info/METADATA
direqt-1.0.0.dist-info/WHEEL
direqt-1.0.0.dist-info/top_level.txt
direqt-1.0.0.dist-info/RECORD
