Metadata-Version: 2.1
Name: direqt
Version: 1.0.0
Summary: Client library for Direqt Ads API
Home-page: https://github.com/direqt/direqt-sdk-python
Author: Myk Willis
Author-email: myk@direqt.io
License: Apache License 2.0
Platform: any
Classifier: Development Status :: 4 - Beta
Classifier: Programming Language :: Python :: 3
License-File: LICENSE
Requires-Dist: google-auth
Requires-Dist: requests
Requires-Dist: requests-toolbelt
